{
	"errno": 0,
	"data": [
		{
			"img":"35.jpg",
			"id":"28",
			"num":"0",
			"title":"奶酪三角面包  ",
			"price":"￥8",
			"text":"焦软的面包片辅以丰富的馅料，是不错的正餐之选。"
		},
		{
			"img":"82.jpg",
			"id":"29",
			"num":"0",
			"title":"黄金乳酪面包",
			"price":"￥12",
			"text":"外皮焦黄，内部松软，干酪香醇。"
		},
		{
			"img":"85.jpg",
			"id":"30",
			"num":"0",
			"title":"乳酪宝岛面包",
			"price":"￥8",
			"text":"满满的乳酪，一直受乳酪爱好者的追捧"
		},
		{
			"img":"51.jpg",
			"id":"31",
			"num":"0",
			"title":"全麦吐司面包",
			"price":"￥9",
			"text":"选用天然奶油，12小时低温发酵，味多美不添加防腐剂。"
		},
		{
			"img":"45.jpg",
			"id":"32",
			"num":"0",
			"title":"全麦蔓越莓核桃面包",
			"price":"￥9",
			"text":"选用美国蔓越莓(国内分装)。"
		},
		{
			"img":"89.jpg",
			"id":"33",
			"num":"0",
			"title":"奶酪拿破仑糕点",
			"price":"￥9",
			"text":"层层酥脆，奶香馥郁"
		},
		{
			"img":"15.jpg",
			"id":"34",
			"num":"0",
			"title":"巧巧核桃圈",
			"price":"￥16",
			"text":"选用美国核桃仁(国内分装)，享受牙齿叩击坚果的乐趣"
		},
		{
			"img":"58.jpg",
			"id":"35",
			"num":"0",
			"title":"核桃堡面包",
			"price":"￥26",
			"text":"焦脆美味的核桃，唤醒疲惫的味觉。"
		},
		{
			"img":"09.jpg",
			"id":"36",
			"num":"0",
			"title":"扁桃仁蛋糕2枚",
			"price":"￥13",
			"text":"选用美国扁桃仁"
		},
		{
			"img":"24.jpg",
			"id":"37",
			"num":"0",
			"title":"枫糖牛角面包（6个/袋）",
			"price":"￥10",
			"text":"选用加拿大枫树糖浆。"
		},
		{
			"img":"33.jpg",
			"id":"38",
			"num":"0",
			"title":"法棍面包",
			"price":"￥12",
			"text":"选用法国活性酵母制作酸面种，外酥内软。"
		},
		{
			"img":"42.jpg",
			"id":"39",
			"num":"0",
			"title":"牛肉松面包",
			"price":"￥8.5",
			"text":"满满肉松，满足你对肉松面包的所有幻想。"
		},
		{
			"img":"41.jpg",
			"id":"40",
			"num":"0",
			"title":"毛毛虫面包",
			"price":"￥8",
			"text":"搞怪的毛毛虫造型，回归童年的奶油夹心面包。"
		},
		{
			"img":"23.jpg",
			"id":"41",
			"num":"0",
			"title":"帕玛森芝士棒面包(6根）",
			"price":"￥13",
			"text":"选用帕玛森干酪、天然奶油（黄油）。"
		},
		{
			"img":"27.jpg",
			"id":"42",
			"num":"0",
			"title":"乳酪金砖面包",
			"price":"￥10",
			"text":"选用进口干酪,足有八十层的美味金砖面包."
		},
		{
			"img":"70.jpg",
			"id":"43",
			"num":"0",
			"title":"葵雅蔓面包（2粒/盒）",
			"price":"￥12",
			"text":"选用美国扁桃仁粉、天然奶油（黄油），法国布列塔尼名产。"
		},
		{
			"img":"06.jpg",
			"id":"44",
			"num":"0",
			"title":"蒜蓉法棍面包",
			"price":"￥13.9",
			"text":"选用法国活性酵母制作酸面种，表皮酥脆、内部松软。"
		},
		{
			"img":"90.jpg",
			"id":"45",
			"num":"0",
			"title":"香榭布里欧面包",
			"price":"￥8",
			"text":"选用美国葡萄干,100%使用法国或英国天然稀奶油."
		},
		{
			"img":"47.jpg",
			"id":"46",
			"num":"0",
			"title":"提子多面包",
			"price":"￥8.5",
			"text":"满口葡萄干，口口有料。"
		},
		{
			"img":"39.jpg",
			"id":"47",
			"num":"0",
			"title":"巧克力金砖面包",
			"price":"￥26",
			"text":"巧克力金砖面包选用进口巧克力。"
		},
		{
			"img":"40.jpg",
			"id":"48",
			"num":"0",
			"title":"菠萝巨无霸面包",
			"price":"￥16",
			"text":"选用天然奶油，12小时低温发酵，味多美不添加防腐剂。"
		},
		{
			"img":"03.jpg",
			"id":"49",
			"num":"0",
			"title":"辣松面包",
			"price":"￥8",
			"text":"丰富的辣味肉松，献给无辣不欢的人。 "
		},
		{
			"img":"04.jpg",
			"id":"50",
			"num":"0",
			"title":"香蒜面包  ",
			"price":"￥8",
			"text":"蒜香浓郁，寻找对味儿的人。"
		},
		{
			"img":"44.jpg",
			"id":"51",
			"num":"0",
			"title":"椰蓉吐司面包",
			"price":"￥17",
			"text":"选用菲律宾椰蓉、天然奶油，12小时低温发酵。"
		},
		{
			"img":"50.jpg",
			"id":"52",
			"num":"0",
			"title":"淡奶吐司面包",
			"price":"￥9",
			"text":"选用天然奶油，味多美不添加防腐剂。"
		},
		{
			"img":"20.jpg",
			"id":"53",
			"num":"0",
			"title":"丹麦三文治",
			"price":"￥12",
			"text":"层次丰富，用多种口感捕获你的味蕾。"
		},
		{
			"img":"19.jpg",
			"id":"54",
			"num":"0",
			"title":"吞拿鱼三文治面包",
			"price":"￥13",
			"text":"多种馅料搭配，营养丰富。"
		},
		{
			"img":"43.jpg",
			"id":"55",
			"num":"0",
			"title":"牛角面包",
			"price":"￥6",
			"text":""
		},
		{
			"img":"16.jpg",
			"id":"56",
			"num":"0",
			"title":"芝士薯泥三文治",
			"price":"￥12",
			"text":"阳光芝士，为早餐加活力。"
		},
		{
			"img":"83.jpg",
			"id":"57",
			"num":"0",
			"title":"罗宋面包",
			"price":"￥8",
			"text":"烘烤的温度，恰好能吃出面包香"
		},
		{
			"img":"57.jpg",
			"id":"58",
			"num":"0",
			"title":"黑美人面包",
			"price":"￥9",
			"text":"巧克力的集结地，从外到内品尝不同层次，不同味道的巧克力。"
		},
		{
			"img":"81.jpg",
			"id":"59",
			"num":"0",
			"title":"杂粮奶酪面包",
			"price":"￥16",
			"text":"杂粮均衡营养，轻盈口感与厚重干酪在口中撞击。"
		},
		{
			"img":"84.jpg",
			"id":"60",
			"num":"0",
			"title":"抹茶奶露面包",
			"price":"￥8.5",
			"text":"抹茶粉恰到好处的中和过多的甜腻。"
		},
		{
			"img":"14.jpg",
			"id":"61",
			"num":"0",
			"title":"芝士热狗面包",
			"price":"￥9",
			"text":"芝士热狗充满早餐的热情，给你一整天活力。"
		},
		{
			"img":"17.jpg",
			"id":"62",
			"num":"0",
			"title":"巧克力旋风",
			"price":"￥9",
			"text":"陷入巧克力的幸福旋涡，就像遇见爱情一样。"
		},
		{
			"img":"59.jpg",
			"id":"63",
			"num":"0",
			"title":"核桃奶露面包",
			"price":"￥10",
			"text":"选用天然奶油（稀奶油）"
		},
		{
			"img":"10.jpg",
			"id":"64",
			"num":"0",
			"title":"热狗卷面包",
			"price":"￥8",
			"text":"经典欧美电影桥段中的日常之食，简单有味。"
		},
		{
			"img":"05.jpg",
			"id":"65",
			"num":"0",
			"title":"豆沙吐司面包",
			"price":"￥17",
			"text":"选用天然奶油，12小时低温发酵"
		},
		{
			"img":"07.jpg",
			"id":"66",
			"num":"0",
			"title":"牛奶吐司面包 ",
			"price":"￥9",
			"text":"选用天然奶油，12小时低温发酵。"
		},
		{
			"img":"25.jpg",
			"id":"67",
			"num":"0",
			"title":"糖醇全麦吐司面包",
			"price":"￥9",
			"text":"选用天然奶油，加入全麦粉，12小时低温发酵。"
		},
		{
			"img":"26.jpg",
			"id":"68",
			"num":"0",
			"title":"老婆饼6枚（口味随机）",
			"price":"￥12",
			"text":"糯米老婆饼选用泰国糯米粉，世代传承的技艺。"
		},
		{
			"img":"64.jpg",
			"id":"69",
			"num":"0",
			"title":"葡式蛋挞2枚",
			"price":"￥12",
			"text":"挞馅选用再制干酪，选用进口天然稀奶油"
		},
		{
			"img":"46.jpg",
			"id":"70",
			"num":"0",
			"title":"雪山之恋芝士派糕点",
			"price":"￥38",
			"text":"选用进口干酪，源自阿尔卑斯山之巅的爱恋"
		}
	]
}